{
  "types": {
    "Person": {
      "name": "Person",
      "kind": "entity",
      "aliases": [],
      "source": "kb_symbol_table"
    }
  },
  "predicates": {
    "provides_proof_of_belgian_nationality": {
      "name": "provides_proof_of_belgian_nationality",
      "args": [
        "Person"
      ],
      "returns": "Bool",
      "kind": "observable",
      "description": "The person provides proof that they possess Belgian nationality.",
      "legal_output": null,
      "output_category": null,
      "directly_observable": true,
      "background": false,
      "case_input": false,
      "assertable_in_case": true,
      "factual_case_input": false,
      "factual_criteria_input": false,
      "case_given_input_predicate": null,
      "query_target_candidate": false,
      "temporal_support": false
    },
    "is_alien": {
      "name": "is_alien",
      "args": [
        "Person"
      ],
      "returns": "Bool",
      "kind": "derived",
      "description": "The person is an alien because they do not provide proof of Belgian nationality.",
      "legal_output": null,
      "output_category": null,
      "directly_observable": false,
      "background": false,
      "case_input": false,
      "assertable_in_case": false,
      "factual_case_input": false,
      "factual_criteria_input": false,
      "case_given_input_predicate": null,
      "query_target_candidate": false,
      "temporal_support": false
    },
    "is_union_citizen": {
      "name": "is_union_citizen",
      "args": [
        "Person"
      ],
      "returns": "Bool",
      "kind": "observable",
      "description": "The person is a Union citizen.",
      "legal_output": null,
      "output_category": null,
      "directly_observable": true,
      "background": false,
      "case_input": false,
      "assertable_in_case": true,
      "factual_case_input": false,
      "factual_criteria_input": false,
      "case_given_input_predicate": null,
      "query_target_candidate": false,
      "temporal_support": false
    },
    "enjoys_community_right_of_free_movement": {
      "name": "enjoys_community_right_of_free_movement",
      "args": [
        "Person"
      ],
      "returns": "Bool",
      "kind": "observable",
      "description": "The person enjoys the Community right of free movement as defined in Article 2, point 5, of the Schengen Borders Code.",
      "legal_output": null,
      "output_category": null,
      "directly_observable": true,
      "background": false,
      "case_input": false,
      "assertable_in_case": true,
      "factual_case_input": false,
      "factual_criteria_input": false,
      "case_given_input_predicate": null,
      "query_target_candidate": false,
      "temporal_support": false
    },
    "is_third_country_national": {
      "name": "is_third_country_national",
      "args": [
        "Person"
      ],
      "returns": "Bool",
      "kind": "derived",
      "description": "The person is a third-country national: not a Union citizen and not enjoying the Community right of free movement.",
      "legal_output": null,
      "output_category": null,
      "directly_observable": false,
      "background": false,
      "case_input": false,
      "assertable_in_case": false,
      "factual_case_input": false,
      "factual_criteria_input": false,
      "case_given_input_predicate": null,
      "query_target_candidate": false,
      "temporal_support": false
    },
    "is_present_on_territory": {
      "name": "is_present_on_territory",
      "args": [
        "Person"
      ],
      "returns": "Bool",
      "kind": "observable",
      "description": "The person is present on the territory.",
      "legal_output": null,
      "output_category": null,
      "directly_observable": true,
      "background": false,
      "case_input": false,
      "assertable_in_case": true,
      "factual_case_input": false,
      "factual_criteria_input": false,
      "case_given_input_predicate": null,
      "query_target_candidate": false,
      "temporal_support": false
    },
    "meets_conditions_for_entry_or_residence": {
      "name": "meets_conditions_for_entry_or_residence",
      "args": [
        "Person"
      ],
      "returns": "Bool",
      "kind": "observable",
      "description": "The alien meets the conditions for entry to or residence on the territory.",
      "legal_output": null,
      "output_category": null,
      "directly_observable": true,
      "background": false,
      "case_input": false,
      "assertable_in_case": true,
      "factual_case_input": false,
      "factual_criteria_input": false,
      "case_given_input_predicate": null,
      "query_target_candidate": false,
      "temporal_support": false
    },
    "previously_met_conditions_for_entry_or_residence": {
      "name": "previously_met_conditions_for_entry_or_residence",
      "args": [
        "Person"
      ],
      "returns": "Bool",
      "kind": "observable",
      "description": "The alien previously met but no longer meets the conditions for entry to or residence on the territory.",
      "legal_output": null,
      "output_category": null,
      "directly_observable": true,
      "background": false,
      "case_input": false,
      "assertable_in_case": true,
      "factual_case_input": false,
      "factual_criteria_input": false,
      "case_given_input_predicate": null,
      "query_target_candidate": false,
      "temporal_support": false
    },
    "has_illegal_residence": {
      "name": "has_illegal_residence",
      "args": [
        "Person"
      ],
      "returns": "Bool",
      "kind": "derived",
      "description": "The alien has illegal residence on the territory.",
      "legal_output": true,
      "output_category": null,
      "directly_observable": false,
      "background": false,
      "case_input": false,
      "assertable_in_case": false,
      "factual_case_input": false,
      "factual_criteria_input": false,
      "case_given_input_predicate": null,
      "query_target_candidate": true,
      "temporal_support": false
    },
    "possesses_valid_travel_document": {
      "name": "possesses_valid_travel_document",
      "args": [
        "Person"
      ],
      "returns": "Bool",
      "kind": "observable",
      "description": "The alien is in possession of a valid travel document.",
      "legal_output": null,
      "output_category": null,
      "directly_observable": true,
      "background": false,
      "case_input": false,
      "assertable_in_case": true,
      "factual_case_input": false,
      "factual_criteria_input": false,
      "case_given_input_predicate": null,
      "query_target_candidate": false,
      "temporal_support": false
    },
    "possesses_valid_passport": {
      "name": "possesses_valid_passport",
      "args": [
        "Person"
      ],
      "returns": "Bool",
      "kind": "observable",
      "description": "The alien is in possession of a valid passport.",
      "legal_output": null,
      "output_category": null,
      "directly_observable": true,
      "background": false,
      "case_input": false,
      "assertable_in_case": true,
      "factual_case_input": false,
      "factual_criteria_input": false,
      "case_given_input_predicate": null,
      "query_target_candidate": false,
      "temporal_support": false
    },
    "possesses_valid_identity_document": {
      "name": "possesses_valid_identity_document",
      "args": [
        "Person"
      ],
      "returns": "Bool",
      "kind": "observable",
      "description": "The alien is in possession of a valid identity document.",
      "legal_output": null,
      "output_category": null,
      "directly_observable": true,
      "background": false,
      "case_input": false,
      "assertable_in_case": true,
      "factual_case_input": false,
      "factual_criteria_input": false,
      "case_given_input_predicate": null,
      "query_target_candidate": false,
      "temporal_support": false
    },
    "recognised_as_national_by_national_authority": {
      "name": "recognised_as_national_by_national_authority",
      "args": [
        "Person"
      ],
      "returns": "Bool",
      "kind": "observable",
      "description": "The alien has been recognised as a national by the national authority of their country.",
      "legal_output": null,
      "output_category": null,
      "directly_observable": true,
      "background": false,
      "case_input": false,
      "assertable_in_case": true,
      "factual_case_input": false,
      "factual_criteria_input": false,
      "case_given_input_predicate": null,
      "query_target_candidate": false,
      "temporal_support": false
    },
    "national_authority_willing_to_issue_laissez_passer": {
      "name": "national_authority_willing_to_issue_laissez_passer",
      "args": [
        "Person"
      ],
      "returns": "Bool",
      "kind": "observable",
      "description": "The national authority of the alien's country has declared itself willing to issue a laissez-passer.",
      "legal_output": null,
      "output_category": null,
      "directly_observable": true,
      "background": false,
      "case_input": false,
      "assertable_in_case": true,
      "factual_case_input": false,
      "factual_criteria_input": false,
      "case_given_input_predicate": null,
      "query_target_candidate": false,
      "temporal_support": false
    },
    "falls_within_nationality_category_for_ministerial_laissez_passer": {
      "name": "falls_within_nationality_category_for_ministerial_laissez_passer",
      "args": [
        "Person"
      ],
      "returns": "Bool",
      "kind": "observable",
      "description": "The alien falls within the category of nationalities for which the minister may personally issue a laissez-passer.",
      "legal_output": null,
      "output_category": null,
      "directly_observable": true,
      "background": false,
      "case_input": false,
      "assertable_in_case": true,
      "factual_case_input": false,
      "factual_criteria_input": false,
      "case_given_input_predicate": null,
      "query_target_candidate": false,
      "temporal_support": false
    },
    "is_identified_alien": {
      "name": "is_identified_alien",
      "args": [
        "Person"
      ],
      "returns": "Bool",
      "kind": "derived",
      "description": "The alien is an identified alien based on possession of valid documents or recognition by national authority.",
      "legal_output": null,
      "output_category": "classification",
      "directly_observable": false,
      "background": false,
      "case_input": false,
      "assertable_in_case": false,
      "factual_case_input": false,
      "factual_criteria_input": false,
      "case_given_input_predicate": null,
      "query_target_candidate": false,
      "temporal_support": false
    },
    "subject_to_removal_procedure": {
      "name": "subject_to_removal_procedure",
      "args": [
        "Person"
      ],
      "returns": "Bool",
      "kind": "observable",
      "description": "The alien is the subject of a removal procedure.",
      "legal_output": null,
      "output_category": null,
      "directly_observable": true,
      "background": false,
      "case_input": false,
      "assertable_in_case": true,
      "factual_case_input": false,
      "factual_criteria_input": false,
      "case_given_input_predicate": null,
      "query_target_candidate": false,
      "temporal_support": false
    },
    "subject_to_international_protection_procedure": {
      "name": "subject_to_international_protection_procedure",
      "args": [
        "Person"
      ],
      "returns": "Bool",
      "kind": "observable",
      "description": "The alien is the subject of a procedure for the granting of international protection.",
      "legal_output": null,
      "output_category": null,
      "directly_observable": true,
      "background": false,
      "case_input": false,
      "assertable_in_case": true,
      "factual_case_input": false,
      "factual_criteria_input": false,
      "case_given_input_predicate": null,
      "query_target_candidate": false,
      "temporal_support": false
    },
    "subject_to_responsible_member_state_determination_procedure": {
      "name": "subject_to_responsible_member_state_determination_procedure",
      "args": [
        "Person"
      ],
      "returns": "Bool",
      "kind": "observable",
      "description": "The alien is the subject of a procedure for determining or transferring to the Member State responsible for examining the application for international protection.",
      "legal_output": null,
      "output_category": null,
      "directly_observable": true,
      "background": false,
      "case_input": false,
      "assertable_in_case": true,
      "factual_case_input": false,
      "factual_criteria_input": false,
      "case_given_input_predicate": null,
      "query_target_candidate": false,
      "temporal_support": false
    },
    "reasons_to_believe_will_abscond": {
      "name": "reasons_to_believe_will_abscond",
      "args": [
        "Person"
      ],
      "returns": "Bool",
      "kind": "helper",
      "description": "There are reasons to believe the alien will abscond, having regard to the objective criteria.",
      "legal_output": null,
      "output_category": null,
      "directly_observable": false,
      "background": false,
      "case_input": false,
      "assertable_in_case": false,
      "factual_case_input": false,
      "factual_criteria_input": false,
      "case_given_input_predicate": null,
      "query_target_candidate": false,
      "temporal_support": false
    },
    "individual_examination_performed": {
      "name": "individual_examination_performed",
      "args": [
        "Person"
      ],
      "returns": "Bool",
      "kind": "observable",
      "description": "An individual examination has been performed for the alien in the context of the risk of absconding assessment.",
      "legal_output": null,
      "output_category": null,
      "directly_observable": true,
      "background": false,
      "case_input": false,
      "assertable_in_case": true,
      "factual_case_input": false,
      "factual_criteria_input": false,
      "case_given_input_predicate": null,
      "query_target_candidate": false,
      "temporal_support": false
    },
    "risk_of_absconding_exists": {
      "name": "risk_of_absconding_exists",
      "args": [
        "Person"
      ],
      "returns": "Bool",
      "kind": "derived",
      "description": "A risk of absconding exists for the alien.",
      "legal_output": true,
      "output_category": null,
      "directly_observable": false,
      "background": false,
      "case_input": false,
      "assertable_in_case": false,
      "factual_case_input": false,
      "factual_criteria_input": false,
      "case_given_input_predicate": null,
      "query_target_candidate": true,
      "temporal_support": false
    },
    "criterion_no_residence_application_after_illegal_entry": {
      "name": "criterion_no_residence_application_after_illegal_entry",
      "args": [
        "Person"
      ],
      "returns": "Bool",
      "kind": "observable",
      "description": "The person did not submit a residence application following their illegal entry.",
      "legal_output": null,
      "output_category": null,
      "directly_observable": true,
      "background": false,
      "case_input": false,
      "assertable_in_case": true,
      "factual_case_input": false,
      "factual_criteria_input": false,
      "case_given_input_predicate": null,
      "query_target_candidate": false,
      "temporal_support": false
    },
    "criterion_no_residence_application_during_illegal_residence": {
      "name": "criterion_no_residence_application_during_illegal_residence",
      "args": [
        "Person"
      ],
      "returns": "Bool",
      "kind": "observable",
      "description": "The person did not submit a residence application during their illegal residence.",
      "legal_output": null,
      "output_category": null,
      "directly_observable": true,
      "background": false,
      "case_input": false,
      "assertable_in_case": true,
      "factual_case_input": false,
      "factual_criteria_input": false,
      "case_given_input_predicate": null,
      "query_target_candidate": false,
      "temporal_support": false
    },
    "criterion_no_international_protection_application_within_time_limit": {
      "name": "criterion_no_international_protection_application_within_time_limit",
      "args": [
        "Person"
      ],
      "returns": "Bool",
      "kind": "observable",
      "description": "The person did not make their application for international protection within the time limit provided for by the Act.",
      "legal_output": null,
      "output_category": null,
      "directly_observable": true,
      "background": false,
      "case_input": false,
      "assertable_in_case": true,
      "factual_case_input": false,
      "factual_criteria_input": false,
      "case_given_input_predicate": null,
      "query_target_candidate": false,
      "temporal_support": false
    },
    "absconding_criterion_failure_to_submit_residence_application": {
      "name": "absconding_criterion_failure_to_submit_residence_application",
      "args": [
        "Person"
      ],
      "returns": "Bool",
      "kind": "derived",
      "description": "The absconding criterion based on failure to submit a residence application is met for the person.",
      "legal_output": null,
      "output_category": null,
      "directly_observable": false,
      "background": false,
      "case_input": false,
      "assertable_in_case": false,
      "factual_case_input": true,
      "factual_criteria_input": false,
      "case_given_input_predicate": "case_given_absconding_criterion_failure_to_submit_residence_application",
      "query_target_candidate": false,
      "temporal_support": false
    },
    "used_false_or_misleading_information_in_procedure": {
      "name": "used_false_or_misleading_information_in_procedure",
      "args": [
        "Person"
      ],
      "returns": "Bool",
      "kind": "observable",
      "description": "The person used false or misleading information in the context of a relevant procedure.",
      "legal_output": null,
      "output_category": null,
      "directly_observable": true,
      "background": false,
      "case_input": false,
      "assertable_in_case": true,
      "factual_case_input": false,
      "factual_criteria_input": false,
      "case_given_input_predicate": null,
      "query_target_candidate": false,
      "temporal_support": false
    },
    "used_false_or_falsified_documents_in_procedure": {
      "name": "used_false_or_falsified_documents_in_procedure",
      "args": [
        "Person"
      ],
      "returns": "Bool",
      "kind": "observable",
      "description": "The person used false or falsified documents in the context of a relevant procedure.",
      "legal_output": null,
      "output_category": null,
      "directly_observable": true,
      "background": false,
      "case_input": false,
      "assertable_in_case": true,
      "factual_case_input": false,
      "factual_criteria_input": false,
      "case_given_input_predicate": null,
      "query_target_candidate": false,
      "temporal_support": false
    },
    "committed_fraud_in_procedure": {
      "name": "committed_fraud_in_procedure",
      "args": [
        "Person"
      ],
      "returns": "Bool",
      "kind": "observable",
      "description": "The person committed fraud in the context of a relevant procedure.",
      "legal_output": null,
      "output_category": null,
      "directly_observable": true,
      "background": false,
      "case_input": false,
      "assertable_in_case": true,
      "factual_case_input": false,
      "factual_criteria_input": false,
      "case_given_input_predicate": null,
      "query_target_candidate": false,
      "temporal_support": false
    },
    "used_other_unlawful_means_in_procedure": {
      "name": "used_other_unlawful_means_in_procedure",
      "args": [
        "Person"
      ],
      "returns": "Bool",
      "kind": "observable",
      "description": "The person used other unlawful means in the context of a relevant procedure.",
      "legal_output": null,
      "output_category": null,
      "directly_observable": true,
      "background": false,
      "case_input": false,
      "assertable_in_case": true,
      "factual_case_input": false,
      "factual_criteria_input": false,
      "case_given_input_predicate": null,
      "query_target_candidate": false,
      "temporal_support": false
    },
    "absconding_criterion_false_information_or_documents": {
      "name": "absconding_criterion_false_information_or_documents",
      "args": [
        "Person"
      ],
      "returns": "Bool",
      "kind": "derived",
      "description": "The absconding criterion based on use of false information or documents is met for the person.",
      "legal_output": null,
      "output_category": null,
      "directly_observable": false,
      "background": false,
      "case_input": false,
      "assertable_in_case": false,
      "factual_case_input": true,
      "factual_criteria_input": false,
      "case_given_input_predicate": "case_given_absconding_criterion_false_information_or_documents",
      "query_target_candidate": false,
      "temporal_support": false
    },
    "does_not_cooperate_with_authorities": {
      "name": "does_not_cooperate_with_authorities",
      "args": [
        "Person"
      ],
      "returns": "Bool",
      "kind": "observable",
      "description": "The person does not cooperate or has not cooperated with the authorities responsible for enforcement of alien regulations.",
      "legal_output": null,
      "output_category": null,
      "directly_observable": true,
      "background": false,
      "case_input": false,
      "assertable_in_case": true,
      "factual_case_input": false,
      "factual_criteria_input": false,
      "case_given_input_predicate": null,
      "query_target_candidate": false,
      "temporal_support": false
    },
    "absconding_criterion_non_cooperation": {
      "name": "absconding_criterion_non_cooperation",
      "args": [
        "Person"
      ],
      "returns": "Bool",
      "kind": "derived",
      "description": "The absconding criterion based on non-cooperation with authorities is met for the person.",
      "legal_output": null,
      "output_category": null,
      "directly_observable": false,
      "background": false,
      "case_input": false,
      "assertable_in_case": false,
      "factual_case_input": true,
      "factual_criteria_input": false,
      "case_given_input_predicate": "case_given_absconding_criterion_non_cooperation",
      "query_target_candidate": false,
      "temporal_support": false
    },
    "declared_unwillingness_to_comply_with_transfer_refusal_removal": {
      "name": "declared_unwillingness_to_comply_with_transfer_refusal_removal",
      "args": [
        "Person"
      ],
      "returns": "Bool",
      "kind": "observable",
      "description": "The person has made clear they do not wish to comply with a transfer, refusal-of-entry, or removal measure.",
      "legal_output": null,
      "output_category": null,
      "directly_observable": true,
      "background": false,
      "case_input": false,
      "assertable_in_case": true,
      "factual_case_input": false,
      "factual_criteria_input": false,
      "case_given_input_predicate": null,
      "query_target_candidate": false,
      "temporal_support": false
    },
    "failed_to_comply_with_transfer_refusal_removal": {
      "name": "failed_to_comply_with_transfer_refusal_removal",
      "args": [
        "Person"
      ],
      "returns": "Bool",
      "kind": "observable",
      "description": "The person has already failed to comply with a transfer, refusal-of-entry, or removal measure.",
      "legal_output": null,
      "output_category": null,
      "directly_observable": true,
      "background": false,
      "case_input": false,
      "assertable_in_case": true,
      "factual_case_input": false,
      "factual_criteria_input": false,
      "case_given_input_predicate": null,
      "query_target_candidate": false,
      "temporal_support": false
    },
    "declared_unwillingness_to_comply_with_entry_ban": {
      "name": "declared_unwillingness_to_comply_with_entry_ban",
      "args": [
        "Person"
      ],
      "returns": "Bool",
      "kind": "observable",
      "description": "The person has made clear they do not wish to comply with an entry ban that has neither been lifted nor suspended.",
      "legal_output": null,
      "output_category": null,
      "directly_observable": true,
      "background": false,
      "case_input": false,
      "assertable_in_case": true,
      "factual_case_input": false,
      "factual_criteria_input": false,
      "case_given_input_predicate": null,
      "query_target_candidate": false,
      "temporal_support": false
    },
    "failed_to_comply_with_entry_ban": {
      "name": "failed_to_comply_with_entry_ban",
      "args": [
        "Person"
      ],
      "returns": "Bool",
      "kind": "observable",
      "description": "The person has already failed to comply with an entry ban that has neither been lifted nor suspended.",
      "legal_output": null,
      "output_category": null,
      "directly_observable": true,
      "background": false,
      "case_input": false,
      "assertable_in_case": true,
      "factual_case_input": false,
      "factual_criteria_input": false,
      "case_given_input_predicate": null,
      "query_target_candidate": false,
      "temporal_support": false
    },
    "declared_unwillingness_to_comply_with_less_coercive_measure": {
      "name": "declared_unwillingness_to_comply_with_less_coercive_measure",
      "args": [
        "Person"
      ],
      "returns": "Bool",
      "kind": "observable",
      "description": "The person has made clear they do not wish to comply with a less coercive measure than deprivation of liberty aimed at guaranteeing transfer, refusal of entry, or removal.",
      "legal_output": null,
      "output_category": null,
      "directly_observable": true,
      "background": false,
      "case_input": false,
      "assertable_in_case": true,
      "factual_case_input": false,
      "factual_criteria_input": false,
      "case_given_input_predicate": null,
      "query_target_candidate": false,
      "temporal_support": false
    },
    "failed_to_comply_with_less_coercive_measure": {
      "name": "failed_to_comply_with_less_coercive_measure",
      "args": [
        "Person"
      ],
      "returns": "Bool",
      "kind": "observable",
      "description": "The person has already failed to comply with a less coercive measure than deprivation of liberty aimed at guaranteeing transfer, refusal of entry, or removal.",
      "legal_output": null,
      "output_category": null,
      "directly_observable": true,
      "background": false,
      "case_input": false,
      "assertable_in_case": true,
      "factual_case_input": false,
      "factual_criteria_input": false,
      "case_given_input_predicate": null,
      "query_target_candidate": false,
      "temporal_support": false
    },
    "declared_unwillingness_to_comply_with_liberty_restricting_measure": {
      "name": "declared_unwillingness_to_comply_with_liberty_restricting_measure",
      "args": [
        "Person"
      ],
      "returns": "Bool",
      "kind": "observable",
      "description": "The person has made clear they do not wish to comply with a liberty-restricting measure aimed at guaranteeing public order or national security.",
      "legal_output": null,
      "output_category": null,
      "directly_observable": true,
      "background": false,
      "case_input": false,
      "assertable_in_case": true,
      "factual_case_input": false,
      "factual_criteria_input": false,
      "case_given_input_predicate": null,
      "query_target_candidate": false,
      "temporal_support": false
    },
    "failed_to_comply_with_liberty_restricting_measure": {
      "name": "failed_to_comply_with_liberty_restricting_measure",
      "args": [
        "Person"
      ],
      "returns": "Bool",
      "kind": "observable",
      "description": "The person has already failed to comply with a liberty-restricting measure aimed at guaranteeing public order or national security.",
      "legal_output": null,
      "output_category": null,
      "directly_observable": true,
      "background": false,
      "case_input": false,
      "assertable_in_case": true,
      "factual_case_input": false,
      "factual_criteria_input": false,
      "case_given_input_predicate": null,
      "query_target_candidate": false,
      "temporal_support": false
    },
    "declared_unwillingness_to_comply_with_equivalent_member_state_measure": {
      "name": "declared_unwillingness_to_comply_with_equivalent_member_state_measure",
      "args": [
        "Person"
      ],
      "returns": "Bool",
      "kind": "observable",
      "description": "The person has made clear they do not wish to comply with a measure taken by another Member State equivalent to a transfer, refusal-of-entry, removal, entry ban, less coercive, or liberty-restricting measure.",
      "legal_output": null,
      "output_category": null,
      "directly_observable": true,
      "background": false,
      "case_input": false,
      "assertable_in_case": true,
      "factual_case_input": false,
      "factual_criteria_input": false,
      "case_given_input_predicate": null,
      "query_target_candidate": false,
      "temporal_support": false
    },
    "failed_to_comply_with_equivalent_member_state_measure": {
      "name": "failed_to_comply_with_equivalent_member_state_measure",
      "args": [
        "Person"
      ],
      "returns": "Bool",
      "kind": "observable",
      "description": "The person has already failed to comply with a measure taken by another Member State equivalent to a transfer, refusal-of-entry, removal, entry ban, less coercive, or liberty-restricting measure.",
      "legal_output": null,
      "output_category": null,
      "directly_observable": true,
      "background": false,
      "case_input": false,
      "assertable_in_case": true,
      "factual_case_input": false,
      "factual_criteria_input": false,
      "case_given_input_predicate": null,
      "query_target_candidate": false,
      "temporal_support": false
    },
    "absconding_criterion_failure_to_comply_with_measures": {
      "name": "absconding_criterion_failure_to_comply_with_measures",
      "args": [
        "Person"
      ],
      "returns": "Bool",
      "kind": "derived",
      "description": "The absconding criterion based on failure to comply with measures is met for the person.",
      "legal_output": null,
      "output_category": null,
      "directly_observable": false,
      "background": false,
      "case_input": false,
      "assertable_in_case": false,
      "factual_case_input": true,
      "factual_criteria_input": false,
      "case_given_input_predicate": "case_given_absconding_criterion_failure_to_comply_with_measures",
      "query_target_candidate": false,
      "temporal_support": false
    },
    "subject_to_active_entry_ban_in_kingdom": {
      "name": "subject_to_active_entry_ban_in_kingdom",
      "args": [
        "Person"
      ],
      "returns": "Bool",
      "kind": "observable",
      "description": "The person is the subject of an entry ban in the Kingdom that has neither been lifted nor suspended.",
      "legal_output": null,
      "output_category": null,
      "directly_observable": true,
      "background": false,
      "case_input": false,
      "assertable_in_case": true,
      "factual_case_input": false,
      "factual_criteria_input": false,
      "case_given_input_predicate": null,
      "query_target_candidate": false,
      "temporal_support": false
    },
    "subject_to_active_entry_ban_in_other_member_state": {
      "name": "subject_to_active_entry_ban_in_other_member_state",
      "args": [
        "Person"
      ],
      "returns": "Bool",
      "kind": "observable",
      "description": "The person is the subject of an entry ban in another Member State that has neither been lifted nor suspended.",
      "legal_output": null,
      "output_category": null,
      "directly_observable": true,
      "background": false,
      "case_input": false,
      "assertable_in_case": true,
      "factual_case_input": false,
      "factual_criteria_input": false,
      "case_given_input_predicate": null,
      "query_target_candidate": false,
      "temporal_support": false
    },
    "absconding_criterion_existing_entry_ban": {
      "name": "absconding_criterion_existing_entry_ban",
      "args": [
        "Person"
      ],
      "returns": "Bool",
      "kind": "derived",
      "description": "The absconding criterion based on an existing entry ban is met for the person.",
      "legal_output": null,
      "output_category": null,
      "directly_observable": false,
      "background": false,
      "case_input": false,
      "assertable_in_case": false,
      "factual_case_input": true,
      "factual_criteria_input": false,
      "case_given_input_predicate": "case_given_absconding_criterion_existing_entry_ban",
      "query_target_candidate": false,
      "temporal_support": false
    },
    "submitted_new_residence_application_after_refusal_or_termination": {
      "name": "submitted_new_residence_application_after_refusal_or_termination",
      "args": [
        "Person"
      ],
      "returns": "Bool",
      "kind": "observable",
      "description": "The person submitted a new residence application immediately after a decision refusing entry or residence, terminating residence, or a refusal-of-entry or removal measure.",
      "legal_output": null,
      "output_category": null,
      "directly_observable": true,
      "background": false,
      "case_input": false,
      "assertable_in_case": true,
      "factual_case_input": false,
      "factual_criteria_input": false,
      "case_given_input_predicate": null,
      "query_target_candidate": false,
      "temporal_support": false
    },
    "submitted_new_protection_application_after_refusal_or_termination": {
      "name": "submitted_new_protection_application_after_refusal_or_termination",
      "args": [
        "Person"
      ],
      "returns": "Bool",
      "kind": "observable",
      "description": "The person submitted a new application for international protection immediately after a decision refusing entry or residence, terminating residence, or a refusal-of-entry or removal measure.",
      "legal_output": null,
      "output_category": null,
      "directly_observable": true,
      "background": false,
      "case_input": false,
      "assertable_in_case": true,
      "factual_case_input": false,
      "factual_criteria_input": false,
      "case_given_input_predicate": null,
      "query_target_candidate": false,
      "temporal_support": false
    },
    "absconding_criterion_new_application_after_negative_decision": {
      "name": "absconding_criterion_new_application_after_negative_decision",
      "args": [
        "Person"
      ],
      "returns": "Bool",
      "kind": "derived",
      "description": "The absconding criterion based on submission of a new application immediately after a negative decision is met for the person.",
      "legal_output": null,
      "output_category": null,
      "directly_observable": false,
      "background": false,
      "case_input": false,
      "assertable_in_case": false,
      "factual_case_input": false,
      "factual_criteria_input": false,
      "case_given_input_predicate": null,
      "query_target_candidate": true,
      "temporal_support": false
    },
    "questioned_about_prior_fingerprints": {
      "name": "questioned_about_prior_fingerprints",
      "args": [
        "Person"
      ],
      "returns": "Bool",
      "kind": "observable",
      "description": "The person was questioned about prior fingerprints.",
      "legal_output": null,
      "output_category": null,
      "directly_observable": true,
      "background": false,
      "case_input": false,
      "assertable_in_case": true,
      "factual_case_input": false,
      "factual_criteria_input": false,
      "case_given_input_predicate": null,
      "query_target_candidate": false,
      "temporal_support": false
    },
    "concealed_prior_fingerprints_in_other_state": {
      "name": "concealed_prior_fingerprints_in_other_state",
      "args": [
        "Person"
      ],
      "returns": "Bool",
      "kind": "observable",
      "description": "The person concealed the fact that they had already provided their fingerprints in another State bound by European regulations on determining the responsible State for international protection.",
      "legal_output": null,
      "output_category": null,
      "directly_observable": true,
      "background": false,
      "case_input": false,
      "assertable_in_case": true,
      "factual_case_input": false,
      "factual_criteria_input": false,
      "case_given_input_predicate": null,
      "query_target_candidate": false,
      "temporal_support": false
    },
    "absconding_criterion_concealment_of_prior_fingerprints": {
      "name": "absconding_criterion_concealment_of_prior_fingerprints",
      "args": [
        "Person"
      ],
      "returns": "Bool",
      "kind": "derived",
      "description": "The absconding criterion based on concealment of prior fingerprints is met for the person.",
      "legal_output": null,
      "output_category": null,
      "directly_observable": false,
      "background": false,
      "case_input": false,
      "assertable_in_case": false,
      "factual_case_input": true,
      "factual_criteria_input": false,
      "case_given_input_predicate": "case_given_absconding_criterion_concealment_of_prior_fingerprints",
      "query_target_candidate": false,
      "temporal_support": false
    },
    "submitted_multiple_protection_applications_with_negative_outcomes": {
      "name": "submitted_multiple_protection_applications_with_negative_outcomes",
      "args": [
        "Person"
      ],
      "returns": "Bool",
      "kind": "observable",
      "description": "The person submitted multiple applications for international protection in the Kingdom or other Member States that gave rise to a negative decision or did not result in a residence permit.",
      "legal_output": null,
      "output_category": null,
      "directly_observable": true,
      "background": false,
      "case_input": false,
      "assertable_in_case": true,
      "factual_case_input": false,
      "factual_criteria_input": false,
      "case_given_input_predicate": null,
      "query_target_candidate": false,
      "temporal_support": false
    },
    "submitted_multiple_residence_applications_with_negative_outcomes": {
      "name": "submitted_multiple_residence_applications_with_negative_outcomes",
      "args": [
        "Person"
      ],
      "returns": "Bool",
      "kind": "observable",
      "description": "The person submitted multiple residence applications in the Kingdom or other Member States that gave rise to a negative decision or did not result in a residence permit.",
      "legal_output": null,
      "output_category": null,
      "directly_observable": true,
      "background": false,
      "case_input": false,
      "assertable_in_case": true,
      "factual_case_input": false,
      "factual_criteria_input": false,
      "case_given_input_predicate": null,
      "query_target_candidate": false,
      "temporal_support": false
    },
    "absconding_criterion_multiple_applications_with_negative_outcomes": {
      "name": "absconding_criterion_multiple_applications_with_negative_outcomes",
      "args": [
        "Person"
      ],
      "returns": "Bool",
      "kind": "derived",
      "description": "The absconding criterion based on multiple applications with negative outcomes is met for the person.",
      "legal_output": null,
      "output_category": null,
      "directly_observable": false,
      "background": false,
      "case_input": false,
      "assertable_in_case": false,
      "factual_case_input": true,
      "factual_criteria_input": false,
      "case_given_input_predicate": "case_given_absconding_criterion_multiple_applications_with_negative_outcomes",
      "query_target_candidate": false,
      "temporal_support": false
    },
    "questioned_about_prior_protection_applications": {
      "name": "questioned_about_prior_protection_applications",
      "args": [
        "Person"
      ],
      "returns": "Bool",
      "kind": "observable",
      "description": "The person was questioned about prior applications for international protection.",
      "legal_output": null,
      "output_category": null,
      "directly_observable": true,
      "background": false,
      "case_input": false,
      "assertable_in_case": true,
      "factual_case_input": false,
      "factual_criteria_input": false,
      "case_given_input_predicate": null,
      "query_target_candidate": false,
      "temporal_support": false
    },
    "concealed_prior_protection_application_in_other_state": {
      "name": "concealed_prior_protection_application_in_other_state",
      "args": [
        "Person"
      ],
      "returns": "Bool",
      "kind": "observable",
      "description": "The person concealed the fact that they had previously submitted an application for international protection in another State bound by European regulations on determining the responsible State.",
      "legal_output": null,
      "output_category": null,
      "directly_observable": true,
      "background": false,
      "case_input": false,
      "assertable_in_case": true,
      "factual_case_input": false,
      "factual_criteria_input": false,
      "case_given_input_predicate": null,
      "query_target_candidate": false,
      "temporal_support": false
    },
    "absconding_criterion_concealment_of_prior_protection_application": {
      "name": "absconding_criterion_concealment_of_prior_protection_application",
      "args": [
        "Person"
      ],
      "returns": "Bool",
      "kind": "derived",
      "description": "The absconding criterion based on concealment of a prior international protection application is met for the person.",
      "legal_output": null,
      "output_category": null,
      "directly_observable": false,
      "background": false,
      "case_input": false,
      "assertable_in_case": false,
      "factual_case_input": true,
      "factual_criteria_input": false,
      "case_given_input_predicate": "case_given_absconding_criterion_concealment_of_prior_protection_application",
      "query_target_candidate": false,
      "temporal_support": false
    },
    "declared_purpose_differs_from_application_purpose": {
      "name": "declared_purpose_differs_from_application_purpose",
      "args": [
        "Person"
      ],
      "returns": "Bool",
      "kind": "observable",
      "description": "The person declared that they came to the Kingdom for purposes other than those for which they submitted an application for international protection or a residence application.",
      "legal_output": null,
      "output_category": null,
      "directly_observable": true,
      "background": false,
      "case_input": false,
      "assertable_in_case": true,
      "factual_case_input": false,
      "factual_criteria_input": false,
      "case_given_input_predicate": null,
      "query_target_candidate": false,
      "temporal_support": false
    },
    "apparent_purpose_differs_from_application_purpose": {
      "name": "apparent_purpose_differs_from_application_purpose",
      "args": [
        "Person"
      ],
      "returns": "Bool",
      "kind": "observable",
      "description": "It appears from the person's file that they came to the Kingdom for purposes other than those for which they submitted an application for international protection or a residence application.",
      "legal_output": null,
      "output_category": null,
      "directly_observable": true,
      "background": false,
      "case_input": false,
      "assertable_in_case": true,
      "factual_case_input": false,
      "factual_criteria_input": false,
      "case_given_input_predicate": null,
      "query_target_candidate": false,
      "temporal_support": false
    },
    "absconding_criterion_declared_or_apparent_purpose_mismatch": {
      "name": "absconding_criterion_declared_or_apparent_purpose_mismatch",
      "args": [
        "Person"
      ],
      "returns": "Bool",
      "kind": "derived",
      "description": "The absconding criterion based on declared or apparent purpose other than stated application is met for the person.",
      "legal_output": null,
      "output_category": null,
      "directly_observable": false,
      "background": false,
      "case_input": false,
      "assertable_in_case": false,
      "factual_case_input": true,
      "factual_criteria_input": false,
      "case_given_input_predicate": "case_given_absconding_criterion_declared_or_apparent_purpose_mismatch",
      "query_target_candidate": false,
      "temporal_support": false
    },
    "subject_to_fine_for_manifestly_unlawful_appeal": {
      "name": "subject_to_fine_for_manifestly_unlawful_appeal",
      "args": [
        "Person"
      ],
      "returns": "Bool",
      "kind": "observable",
      "description": "The person is the subject of a fine because they submitted a manifestly unlawful appeal to the Council for Alien Law Litigation.",
      "legal_output": null,
      "output_category": null,
      "directly_observable": true,
      "background": false,
      "case_input": false,
      "assertable_in_case": true,
      "factual_case_input": false,
      "factual_criteria_input": false,
      "case_given_input_predicate": null,
      "query_target_candidate": false,
      "temporal_support": false
    },
    "absconding_criterion_fine_for_manifestly_unlawful_appeal": {
      "name": "absconding_criterion_fine_for_manifestly_unlawful_appeal",
      "args": [
        "Person"
      ],
      "returns": "Bool",
      "kind": "derived",
      "description": "The absconding criterion based on a fine for a manifestly unlawful appeal is met for the person.",
      "legal_output": null,
      "output_category": null,
      "directly_observable": false,
      "background": false,
      "case_input": false,
      "assertable_in_case": false,
      "factual_case_input": true,
      "factual_criteria_input": false,
      "case_given_input_predicate": "case_given_absconding_criterion_fine_for_manifestly_unlawful_appeal",
      "query_target_candidate": false,
      "temporal_support": false
    },
    "any_absconding_criterion_met": {
      "name": "any_absconding_criterion_met",
      "args": [
        "Person"
      ],
      "returns": "Bool",
      "kind": "helper",
      "description": "At least one objective absconding criterion is met for the person.",
      "legal_output": null,
      "output_category": null,
      "directly_observable": false,
      "background": false,
      "case_input": false,
      "assertable_in_case": false,
      "factual_case_input": true,
      "factual_criteria_input": false,
      "case_given_input_predicate": "case_given_any_absconding_criterion_met",
      "query_target_candidate": false,
      "temporal_support": false
    }
  },
  "functions": {},
  "assertable_case_symbols": {
    "predicates": [
      "apparent_purpose_differs_from_application_purpose",
      "committed_fraud_in_procedure",
      "concealed_prior_fingerprints_in_other_state",
      "concealed_prior_protection_application_in_other_state",
      "criterion_no_international_protection_application_within_time_limit",
      "criterion_no_residence_application_after_illegal_entry",
      "criterion_no_residence_application_during_illegal_residence",
      "declared_purpose_differs_from_application_purpose",
      "declared_unwillingness_to_comply_with_entry_ban",
      "declared_unwillingness_to_comply_with_equivalent_member_state_measure",
      "declared_unwillingness_to_comply_with_less_coercive_measure",
      "declared_unwillingness_to_comply_with_liberty_restricting_measure",
      "declared_unwillingness_to_comply_with_transfer_refusal_removal",
      "does_not_cooperate_with_authorities",
      "enjoys_community_right_of_free_movement",
      "failed_to_comply_with_entry_ban",
      "failed_to_comply_with_equivalent_member_state_measure",
      "failed_to_comply_with_less_coercive_measure",
      "failed_to_comply_with_liberty_restricting_measure",
      "failed_to_comply_with_transfer_refusal_removal",
      "falls_within_nationality_category_for_ministerial_laissez_passer",
      "individual_examination_performed",
      "is_present_on_territory",
      "is_union_citizen",
      "meets_conditions_for_entry_or_residence",
      "national_authority_willing_to_issue_laissez_passer",
      "possesses_valid_identity_document",
      "possesses_valid_passport",
      "possesses_valid_travel_document",
      "previously_met_conditions_for_entry_or_residence",
      "provides_proof_of_belgian_nationality",
      "questioned_about_prior_fingerprints",
      "questioned_about_prior_protection_applications",
      "recognised_as_national_by_national_authority",
      "subject_to_active_entry_ban_in_kingdom",
      "subject_to_active_entry_ban_in_other_member_state",
      "subject_to_fine_for_manifestly_unlawful_appeal",
      "subject_to_international_protection_procedure",
      "subject_to_removal_procedure",
      "subject_to_responsible_member_state_determination_procedure",
      "submitted_multiple_protection_applications_with_negative_outcomes",
      "submitted_multiple_residence_applications_with_negative_outcomes",
      "submitted_new_protection_application_after_refusal_or_termination",
      "submitted_new_residence_application_after_refusal_or_termination",
      "used_false_or_falsified_documents_in_procedure",
      "used_false_or_misleading_information_in_procedure",
      "used_other_unlawful_means_in_procedure"
    ],
    "functions": []
  },
  "factual_case_input_predicates": [
    "absconding_criterion_concealment_of_prior_fingerprints",
    "absconding_criterion_concealment_of_prior_protection_application",
    "absconding_criterion_declared_or_apparent_purpose_mismatch",
    "absconding_criterion_existing_entry_ban",
    "absconding_criterion_failure_to_comply_with_measures",
    "absconding_criterion_failure_to_submit_residence_application",
    "absconding_criterion_false_information_or_documents",
    "absconding_criterion_fine_for_manifestly_unlawful_appeal",
    "absconding_criterion_multiple_applications_with_negative_outcomes",
    "absconding_criterion_non_cooperation",
    "any_absconding_criterion_met"
  ],
  "factual_criteria_input_predicates": [],
  "legal_output_query_targets": [
    "absconding_criterion_new_application_after_negative_decision",
    "has_illegal_residence",
    "risk_of_absconding_exists"
  ],
  "temporal_support_symbols": []
}
