{
  "id": "run_203",
  "law": {
    "path": "example_laws/vreemdelingenwet.txt"
  },
  "case": {
    "text": "Nina legt een geldige Belgische identiteitskaart voor en bewijst daarmee de Belgische nationaliteit."
  },
  "questions": [
    {
      "id": "q1",
      "text": "Valt Nina onder de definitie van een vreemdeling in artikel 1, paragraaf 1, punt 1?",
      "expected": {
        "mode": "boolean",
        "value": false,
        "reason": "A foreigner is anyone who does not provide proof of Belgian nationality; Nina proved Belgian nationality."
      }
    }
  ]
}
