{
  "intent": "deduction",
  "symbolic_status": "ok",
  "status": "ok",
  "scorable": true,
  "detected_question_type": "boolean",
  "selected_intent": "deduction",
  "selected_reason": "expected.mode=boolean",
  "routing": {
    "question": "Is artikel 4.23, paragraaf 4 een reden om Karin het vruchtgebruik van de gezinswoning te weigeren?",
    "detected_question_type": "boolean",
    "selected_intent": "deduction",
    "selected_reason": "expected.mode=boolean",
    "scorable": true,
    "fallback_intent": null,
    "warnings": [],
    "legal_output_symbols": [
      "exception_applies"
    ],
    "query_hint_type": "boolean",
    "expected_question_type": "boolean"
  },
  "satisfiability_check": {
    "stage": "pre_query",
    "kb_case_satisfiable": true,
    "status": "ok",
    "details": "theory satisfiable",
    "intent_backend": "idp_z3.tasks.satisfiable_check",
    "duration_seconds": 0.0727
  },
  "warnings": [],
  "deduction": {
    "intent": "deduction",
    "status": "ok",
    "output_kind": "epistemic_boolean",
    "predicate": "exception_applies",
    "args": [
      "karin",
      "joris"
    ],
    "possible": true,
    "certain": false,
    "label": "unknown",
    "atom": "exception_applies(x0,x1)",
    "constraint": "? x0 in Person, x1 in Person: __sel0(x0) & __sel1(x1) & exception_applies(x0,x1)",
    "certainty_class": "inconclusive",
    "sat": true,
    "internal_intent": "deduction",
    "antecedent_coverage": [
      {
        "rule_index": 0,
        "target": "exception_applies(karin,joris)",
        "conditions": [
          {
            "atom": "is_surviving_cohabiting_partner(karin)",
            "status": "present"
          },
          {
            "atom": "is_predeceased_cohabiting_partner(joris)",
            "status": "present"
          },
          {
            "atom": "is_legally_cohabiting_partner_of(karin,joris)",
            "status": "present"
          },
          {
            "atom": "is_descendant_of(karin,joris)",
            "status": "present"
          }
        ]
      }
    ]
  },
  "model_expansion": null,
  "get_range": null,
  "satisfiable": null,
  "explanation": null,
  "execution_query": {
    "type": "predicate",
    "predicate": "exception_applies",
    "mode": "boolean",
    "args": [
      "karin",
      "joris"
    ],
    "explain": false,
    "predicate_kind": "derived",
    "query_type": "predicate_boolean",
    "internal_intent": "deduction"
  },
  "output_kind": "epistemic_boolean",
  "certainty_class": "inconclusive",
  "predicate": "exception_applies",
  "args": [
    "karin",
    "joris"
  ],
  "label": "unknown",
  "possible": true,
  "certain": false,
  "sat": true,
  "antecedent_coverage": [
    {
      "rule_index": 0,
      "target": "exception_applies(karin,joris)",
      "conditions": [
        {
          "atom": "is_surviving_cohabiting_partner(karin)",
          "status": "present"
        },
        {
          "atom": "is_predeceased_cohabiting_partner(joris)",
          "status": "present"
        },
        {
          "atom": "is_legally_cohabiting_partner_of(karin,joris)",
          "status": "present"
        },
        {
          "atom": "is_descendant_of(karin,joris)",
          "status": "present"
        }
      ]
    }
  ]
}
